nerf_toy/__init__.py
nerf_toy/callback.py
nerf_toy/data_loader.py
nerf_toy/metrics.py
nerf_toy/model.py
nerf_toy/transforms.py
nerf_toy/utils.py
nerf_toy-1.0.0.dist-info/LICENSE
nerf_toy-1.0.0.dist-info/METADATA
nerf_toy-1.0.0.dist-info/WHEEL
nerf_toy-1.0.0.dist-info/top_level.txt
nerf_toy-1.0.0.dist-info/RECORD
