Metadata-Version: 2.1
Name: nerf-toy
Version: 1.0.0
Summary: A 2D toy illustration of Neural Radiance Fields
Home-page: https://github.com/shubhamwagh/nerf-toy
Author: Shubham Wagh
Author-email: shubhamwagh48@gmail.com
License: MIT
Keywords: nerf,neural radiance fields,nerf2D,nerf toy,fourier,positional encoding
Platform: Ubuntu 20.04
Platform: Ubuntu 21.04
Platform: Windows
Classifier: Development Status :: 3 - Alpha
Classifier: License :: OSI Approved :: MIT License
Classifier: Programming Language :: Python
Classifier: Programming Language :: Python :: 3.6
Classifier: Programming Language :: Python :: 3.7
Classifier: Programming Language :: Python :: 3.8
Classifier: Programming Language :: Python :: 3.9
Classifier: Programming Language :: Python :: 3.10
Classifier: Programming Language :: Python :: 3 :: Only
Classifier: Topic :: Software Development :: Libraries
Classifier: Topic :: Software Development :: Libraries :: Python Modules
Classifier: Intended Audience :: Developers
Requires-Python: >=3.6, <4
License-File: LICENSE
Requires-Dist: opencv-python
Requires-Dist: tensorflow
Requires-Dist: imageio
Requires-Dist: imageio-ffmpeg
